snovault/__init__.py
snovault/app.py
snovault/attachment.py
snovault/auditor.py
snovault/authentication.py
snovault/batchupgrade.py
snovault/cache.py
snovault/calculated.py
snovault/config.py
snovault/connection.py
snovault/crud_views.py
snovault/dev_servers.py
snovault/embed.py
snovault/etag.py
snovault/indexing_views.py
snovault/interfaces.py
snovault/invalidation.py
snovault/json_renderer.py
snovault/jsongraph.py
snovault/jsonld_context.py
snovault/nginx-dev.conf
snovault/predicates.py
snovault/resource_views.py
snovault/resources.py
snovault/schema_graph.py
snovault/schema_utils.py
snovault/schema_views.py
snovault/snowflake_hash.py
snovault/stats.py
snovault/storage.py
snovault/typeinfo.py
snovault/upgrader.py
snovault/util.py
snovault/validation.py
snovault/validators.py
snovault/commands/__init__.py
snovault/commands/check_rendering.py
snovault/commands/deploy.py
snovault/commands/es_index_data.py
snovault/commands/jsonld_rdf.py
snovault/commands/profile.py
snovault/commands/spreadsheet_to_json.py
snovault/elasticsearch/__init__.py
snovault/elasticsearch/cached_views.py
snovault/elasticsearch/create_mapping.py
snovault/elasticsearch/es_index_listener.py
snovault/elasticsearch/esstorage.py
snovault/elasticsearch/indexer.py
snovault/elasticsearch/interfaces.py
snovault/elasticsearch/mpindexer.py
snovault/tests/__init__.py
snovault/tests/elasticsearch_fixture.py
snovault/tests/indexfixtures.py
snovault/tests/postgresql_fixture.py
snovault/tests/pyramidfixtures.py
snovault/tests/serverfixtures.py
snovault/tests/test_attachment.py
snovault/tests/test_auditor.py
snovault/tests/test_authentication.py
snovault/tests/test_embedding.py
snovault/tests/test_indexing.py
snovault/tests/test_key.py
snovault/tests/test_link.py
snovault/tests/test_post_put_patch.py
snovault/tests/test_snowflake_hash.py
snovault/tests/test_storage.py
snovault/tests/test_upgrader.py
snovault/tests/testappfixtures.py
snovault-0.23.dist-info/DESCRIPTION.rst
snovault-0.23.dist-info/METADATA
snovault-0.23.dist-info/RECORD
snovault-0.23.dist-info/WHEEL
snovault-0.23.dist-info/entry_points.txt
snovault-0.23.dist-info/metadata.json
snovault-0.23.dist-info/top_level.txt
