Metadata-Version: 2.0
Name: snovault
Version: 0.23
Summary: Snovault Hybrid Object Relational Database Framework
Home-page: http://github.com/ENCODE-DCC/snovault/
Author: Benjamin Hitz
Author-email: hitz@stanford.edu
License: MIT
Platform: UNKNOWN
Classifier: Development Status :: 3 - Alpha
Classifier: Intended Audience :: Developers
Classifier: Intended Audience :: Science/Research
Classifier: Framework :: Pyramid
Classifier: License :: OSI Approved :: MIT License
Classifier: Topic :: Database :: Database Engines/Servers
Classifier: Programming Language :: Python :: 2.7
Classifier: Programming Language :: Python :: 3
Classifier: Programming Language :: Python :: 3.4
Requires-Dist: Pillow
Requires-Dist: PyBrowserID
Requires-Dist: SQLAlchemy (>=1.0.0b1)
Requires-Dist: WSGIProxy2
Requires-Dist: WebTest
Requires-Dist: backports.functools-lru-cache
Requires-Dist: bcrypt
Requires-Dist: boto
Requires-Dist: boto3
Requires-Dist: botocore
Requires-Dist: cryptacular
Requires-Dist: elasticsearch
Requires-Dist: future
Requires-Dist: humanfriendly
Requires-Dist: jmespath
Requires-Dist: jsonschema-serialize-fork
Requires-Dist: loremipsum
Requires-Dist: lucenequery
Requires-Dist: netaddr
Requires-Dist: passlib
Requires-Dist: psutil
Requires-Dist: pyramid
Requires-Dist: pyramid-localroles
Requires-Dist: pyramid-multiauth
Requires-Dist: pyramid-tm
Requires-Dist: python-magic
Requires-Dist: pytz
Requires-Dist: rdflib
Requires-Dist: rdflib-jsonld
Requires-Dist: rfc3987
Requires-Dist: setuptools
Requires-Dist: simplejson
Requires-Dist: strict-rfc3339
Requires-Dist: subprocess-middleware
Requires-Dist: subprocess32
Requires-Dist: xlrd
Requires-Dist: zope.sqlalchemy
Provides-Extra: test
Requires-Dist: pytest (>=2.4.0); extra == 'test'
Requires-Dist: pytest-bdd; extra == 'test'
Requires-Dist: pytest-exact-fixtures; extra == 'test'
Requires-Dist: pytest-mock; extra == 'test'
Requires-Dist: pytest-splinter; extra == 'test'
